mirrorshift/__init__.py
mirrorshift/data.py
mirrorshift/distributed.py
mirrorshift/inference.py
mirrorshift/models.py
mirrorshift/train.py
mirrorshift/utils.py
mirrorshift-0.1.0.dist-info/LICENSE
mirrorshift-0.1.0.dist-info/METADATA
mirrorshift-0.1.0.dist-info/WHEEL
mirrorshift-0.1.0.dist-info/entry_points.txt
mirrorshift-0.1.0.dist-info/top_level.txt
mirrorshift-0.1.0.dist-info/RECORD
