Metadata-Version: 2.2
Name: mirrorshift
Version: 0.1.0
Summary: my personal repo for transformers implementations and experiments
Author-email: Varun Singh <23416001+sapiosaturn@users.noreply.github.com>
License: MIT
Project-URL: Homepage, https://github.com/sapiosaturn/mirrorshift
Project-URL: Bug Tracker, https://github.com/sapiosaturn/mirrorshift/issues
Classifier: Programming Language :: Python :: 3
Classifier: License :: OSI Approved :: MIT License
Classifier: Operating System :: OS Independent
Classifier: Topic :: Scientific/Engineering :: Artificial Intelligence
Classifier: Intended Audience :: Developers
Classifier: Intended Audience :: Science/Research
Requires-Python: >=3.11
License-File: LICENSE
Requires-Dist: torch>=2.5.1
Requires-Dist: tensorboard>=2.18.0
Requires-Dist: tiktoken>=0.8.0
